snakebyte/__init__.py
snakebyte/config.py
snakebyte/game.py
snakebyte/key_config.py
snakebyte/utils.py
snakebyte-1.0.0.dist-info/licenses/LICENSE
snakebyte-1.0.0.dist-info/METADATA
snakebyte-1.0.0.dist-info/WHEEL
snakebyte-1.0.0.dist-info/entry_points.txt
snakebyte-1.0.0.dist-info/top_level.txt
snakebyte-1.0.0.dist-info/RECORD
