Metadata-Version: 2.4
Name: snakebyte
Version: 1.0.0
Summary: A terminal-based snake game with levels, power-ups, and high score tracking.
Author-email: Manav Sharma <manavs19102006@gmail.com>
Project-URL: Homepage, https://github.com/HattoriMan/SnakeByte
Project-URL: Repository, https://github.com/HattoriMan/SnakeByte
Project-URL: Issues, https://github.com/HattoriMan/SnakeByte/issues
Requires-Python: >=3.7
License-File: LICENSE
Requires-Dist: numpy>=1.26.0
Requires-Dist: pyfiglet>=0.8.post1
Requires-Dist: appdirs>=1.4.4
Requires-Dist: windows-curses>=2.4.1; platform_system == "Windows"
Dynamic: license-file
